cloud3d/__init__.py
cloud3d/cloudsat_products.py
cloud3d/constant.py
cloud3d/goes.py
cloud3d/ibtracs_utils.py
cloud3d/model_utils.py
cloud3d/predict.py
cloud3d-0.0.1.dist-info/LICENSE
cloud3d-0.0.1.dist-info/METADATA
cloud3d-0.0.1.dist-info/WHEEL
cloud3d-0.0.1.dist-info/RECORD
