Metadata-Version: 2.1
Name: cloud3d
Version: 0.0.1
Summary: This is a template repository for Python projects that use Poetry for their dependency management.
Home-page: https://github.com/fpgmaas/cloud3d
Author: Florian Maas
Author-email: fpgmaas@gmail.com
Requires-Python: >=3.11,<4.0
Classifier: Programming Language :: Python :: 3
Classifier: Programming Language :: Python :: 3.11
Classifier: Programming Language :: Python :: 3.12
Requires-Dist: earthengine-api (>=1.5.24)
Requires-Dist: geopandas (>=1.1.1)
Requires-Dist: numpy (>=2.0.2)
Requires-Dist: pandas (>=2.2.2)
Requires-Dist: pandas-datareader (>=0.10.0)
Requires-Dist: scipy (>=1.16.0)
Requires-Dist: shapely (>=2.1.1)
Requires-Dist: tqdm (>=4.67.1)
Project-URL: Documentation, https://fpgmaas.github.io/cloud3d/
Project-URL: Repository, https://github.com/fpgmaas/cloud3d
